odoo/addons/shopinvader_customer_validate/README.rst
odoo/addons/shopinvader_customer_validate/__init__.py
odoo/addons/shopinvader_customer_validate/__manifest__.py
odoo/addons/shopinvader_customer_validate/exceptions.py
odoo/addons/shopinvader_customer_validate/hooks.py
odoo/addons/shopinvader_customer_validate/components/__init__.py
odoo/addons/shopinvader_customer_validate/components/partner_mixin.py
odoo/addons/shopinvader_customer_validate/components/partner_validator.py
odoo/addons/shopinvader_customer_validate/components/res_partner_event_listener.py
odoo/addons/shopinvader_customer_validate/components/shopinvader_partner_event_listener.py
odoo/addons/shopinvader_customer_validate/data/email_template.xml
odoo/addons/shopinvader_customer_validate/data/shopinvader_notification.xml
odoo/addons/shopinvader_customer_validate/demo/email_demo.xml
odoo/addons/shopinvader_customer_validate/demo/notification_demo.xml
odoo/addons/shopinvader_customer_validate/i18n/shopinvader_customer_validate.pot
odoo/addons/shopinvader_customer_validate/migrations/14.0.1.2.3/pre-migration.py
odoo/addons/shopinvader_customer_validate/models/__init__.py
odoo/addons/shopinvader_customer_validate/models/res_partner.py
odoo/addons/shopinvader_customer_validate/models/shopinvader_backend.py
odoo/addons/shopinvader_customer_validate/models/shopinvader_notification.py
odoo/addons/shopinvader_customer_validate/models/shopinvader_partner.py
odoo/addons/shopinvader_customer_validate/readme/CONTRIBUTORS.rst
odoo/addons/shopinvader_customer_validate/readme/CREDITS.rst
odoo/addons/shopinvader_customer_validate/readme/DESCRIPTION.rst
odoo/addons/shopinvader_customer_validate/security/ir.model.access.csv
odoo/addons/shopinvader_customer_validate/services/__init__.py
odoo/addons/shopinvader_customer_validate/services/addresses.py
odoo/addons/shopinvader_customer_validate/services/customer.py
odoo/addons/shopinvader_customer_validate/static/description/icon.png
odoo14_addon_shopinvader_customer_validate-14.0.1.4.0.dist-info/METADATA
odoo14_addon_shopinvader_customer_validate-14.0.1.4.0.dist-info/WHEEL
odoo14_addon_shopinvader_customer_validate-14.0.1.4.0.dist-info/top_level.txt
odoo14_addon_shopinvader_customer_validate-14.0.1.4.0.dist-info/RECORD
